sqlalchemy_hana/__init__.py
sqlalchemy_hana/_uuid.py
sqlalchemy_hana/alembic.py
sqlalchemy_hana/dialect.py
sqlalchemy_hana/elements.py
sqlalchemy_hana/errors.py
sqlalchemy_hana/functions.py
sqlalchemy_hana/py.typed
sqlalchemy_hana/types.py
sqlalchemy_hana-4.0.0.dist-info/licenses/LICENSE
sqlalchemy_hana-4.0.0.dist-info/METADATA
sqlalchemy_hana-4.0.0.dist-info/WHEEL
sqlalchemy_hana-4.0.0.dist-info/entry_points.txt
sqlalchemy_hana-4.0.0.dist-info/top_level.txt
sqlalchemy_hana-4.0.0.dist-info/RECORD
