Metadata-Version: 2.4
Name: sqlalchemy-hana
Version: 4.0.0
Summary: SQLAlchemy dialect for SAP HANA
Author-email: Christoph Heer <christoph.heer@sap.com>
Maintainer-email: Christoph Heer <christoph.heer@sap.com>, Kai Harder <kai.harder@sap.com>
License-Expression: Apache-2.0
Project-URL: Repository, https://github.com/SAP/sqlalchemy-hana
Project-URL: Issue Tracker, https://github.com/SAP/sqlalchemy-hana/issues
Project-URL: Changelog, https://github.com/SAP/sqlalchemy-hana/blob/main/CHANGES.rst
Keywords: sqlalchemy,sap,hana
Classifier: Development Status :: 5 - Production/Stable
Classifier: Intended Audience :: Developers
Classifier: Operating System :: OS Independent
Classifier: Programming Language :: Python :: 3 :: Only
Classifier: Programming Language :: Python :: 3.10
Classifier: Programming Language :: Python :: 3.11
Classifier: Programming Language :: Python :: 3.12
Classifier: Programming Language :: Python :: 3.13
Classifier: Programming Language :: Python :: 3.14
Classifier: Programming Language :: SQL
Classifier: Topic :: Database
Classifier: Topic :: Database :: Front-Ends
Classifier: Topic :: Software Development
Classifier: Topic :: Software Development :: Libraries :: Python Modules
Classifier: Typing :: Typed
Requires-Python: ~=3.10
License-File: LICENSE
Requires-Dist: sqlalchemy<3,>=2
Requires-Dist: hdbcli~=2.10
Provides-Extra: alembic
Requires-Dist: alembic~=1.12; extra == "alembic"
Dynamic: license-file
